[
  {
    "name": "Иванов Иван Иванович",
    "books": [
      {
        "name": "Java 2 Том 1 Основы",
        "authors": [
          "Хорстманн",
          "Корнелл"
        ],
        "pages": 816,
        "year": 2010
      },
      {
        "name": "Руслан и Людмила",
        "authors": [
          "Пушкин"
        ],
        "pages": 100,
        "year": 1820
      },
      {
        "name": "Горе от ума",
        "authors": [
          "Грибоедов"
        ],
        "pages": 100,
        "year": 1824
      },
      {
        "name": "Приёмы ООП, паттерны проектирования",
        "authors": [
          "Гамма",
          "Хелм",
          "Джонсон",
          "Влиссидес"
        ],
        "pages": 368,
        "year": 2018
      },
      {
        "name": "React в действии",
        "authors": [
          "Томас"
        ],
        "pages": 368,
        "year": 2019
      }
    ]
  },
  {
    "name": "Петров Петр Петрович",
    "books": [
      {
        "name": "Java 2 Том 1 Основы",
        "authors": [
          "Хорстманн",
          "Корнелл"
        ],
        "pages": 816,
        "year": 2010
      },
      {
        "name": "Конкурентность в C#",
        "authors": [
          "Клири"
        ],
        "pages": 272,
        "year": 2020
      },
      {
        "name": "React в действии",
        "authors": [
          "Томас"
        ],
        "pages": 368,
        "year": 2019
      },
      {
        "name": "Приёмы ООП, паттерны проектирования",
        "authors": [
          "Гамма",
          "хЕЛМ",
          "дЖОНСОН",
          "Влиссидес"
        ],
        "pages": 368,
        "year": 2018
      },
      {
        "name": "Руслан и Людмила",
        "authors": [
          "Пушкин"
        ],
        "pages": 100,
        "year": 1820
      }
    ]
  }
]